<?xml version="1.0" encoding="utf-8"?>
<databaseChangeLog
    xmlns="http://www.liquibase.org/xml/ns/dbchangelog"
    xmlns:ext="http://www.liquibase.org/xml/ns/dbchangelog-ext"
    xmlns:xsi="http://www.w3.org/2001/XMLSchema-instance"
    xsi:schemaLocation="http://www.liquibase.org/xml/ns/dbchangelog http://www.liquibase.org/xml/ns/dbchangelog/dbchangelog-3.5.xsd
                        http://www.liquibase.org/xml/ns/dbchangelog-ext http://www.liquibase.org/xml/ns/dbchangelog/dbchangelog-ext.xsd">

    <property name="now" value="now()" dbms="h2"/>

    <property name="now" value="now()" dbms="mysql"/>
    <property name="autoIncrement" value="true"/>

    <property name="floatType" value="float4" dbms="postgresql, h2"/>
    <property name="floatType" value="float" dbms="mysql, oracle, mssql"/>

    <!--
        Added the entity CommerceItem.
    -->
    <changeSet id="20180913024102-1" author="jhipster">
        <createTable tableName="commerce_item">
            <column name="id" type="bigint" autoIncrement="${autoIncrement}">
                <constraints primaryKey="true" nullable="false"/>
            </column>
            <column name="skuid" type="varchar(255)">
                <constraints nullable="false" />
            </column>

            <column name="quantity" type="integer">
                <constraints nullable="false" />
            </column>

            <column name="creation_date" type="datetime">
                <constraints nullable="false" />
            </column>

            <column name="update_date" type="datetime">
                <constraints nullable="true" />
            </column>

            <column name="commerce_order_id" type="bigint">
                <constraints nullable="true" />
            </column>
            <column name="price_id" type="bigint">
                <constraints unique="true" nullable="true" uniqueConstraintName="ux_commerce_item_price_id" />
            </column>            <column name="ship_info_id" type="bigint">
                <constraints unique="true" nullable="true" uniqueConstraintName="ux_commerce_item_ship_info_id" />
            </column>            <column name="pay_info_id" type="bigint">
                <constraints unique="true" nullable="true" uniqueConstraintName="ux_commerce_item_pay_info_id" />
            </column>
            <!-- jhipster-needle-liquibase-add-column - JHipster will add columns here, do not remove-->
        </createTable>
        <dropDefaultValue tableName="commerce_item" columnName="creation_date" columnDataType="datetime"/>
        <dropDefaultValue tableName="commerce_item" columnName="update_date" columnDataType="datetime"/>
        
        <createTable tableName="commerce_item_shipcontainer">
            <column name="shipcontainers_id" type="bigint">
                <constraints nullable="false"/>
            </column>
            <column name="commerce_items_id" type="bigint">
                <constraints nullable="false"/>
            </column>
        </createTable>

        <addPrimaryKey columnNames="commerce_items_id, shipcontainers_id" tableName="commerce_item_shipcontainer"/>
        
        <createTable tableName="commerce_item_payment">
            <column name="payments_id" type="bigint">
                <constraints nullable="false"/>
            </column>
            <column name="commerce_items_id" type="bigint">
                <constraints nullable="false"/>
            </column>
        </createTable>

        <addPrimaryKey columnNames="commerce_items_id, payments_id" tableName="commerce_item_payment"/>
        
    </changeSet>
    <!-- jhipster-needle-liquibase-add-changeset - JHipster will add changesets here, do not remove-->
</databaseChangeLog>
